package_finder/__init__.py
package_finder/cli.py
package_finder/finders/__init__.py
package_finder/finders/node.py
package_finder/finders/python.py
package_finder-0.1.1.dist-info/METADATA
package_finder-0.1.1.dist-info/WHEEL
package_finder-0.1.1.dist-info/entry_points.txt
package_finder-0.1.1.dist-info/RECORD
